{
  "openapi": "3.0.3",
  "info": {
    "title": "ECommercart API",
    "version": "1.0.0",
    "description": "API documentation for the ECommercart backend."
  },
  "servers": [
    {
      "url": "http://localhost:8000",
      "description": "Local development server"
    }
  ],
  "components": {
    "securitySchemes": {
      "BearerAuth": {
        "type": "http",
        "scheme": "bearer",
        "bearerFormat": "JWT"
      }
    },
    "schemas": {
      "UserRegisterRequest": {
        "type": "object",
        "required": ["name", "email", "password"],
        "properties": {
          "name": {
            "type": "string",
            "example": "Jane Doe"
          },
          "email": {
            "type": "string",
            "format": "email",
            "example": "jane@example.com"
          },
          "password": {
            "type": "string",
            "format": "password",
            "example": "SecurePassword123"
          }
        }
      },
      "UserLoginRequest": {
        "type": "object",
        "required": ["email", "password"],
        "properties": {
          "email": {
            "type": "string",
            "format": "email",
            "example": "jane@example.com"
          },
          "password": {
            "type": "string",
            "format": "password",
            "example": "SecurePassword123"
          }
        }
      },
      "AddItemRequest": {
        "type": "object",
        "required": ["userId", "productId", "productName", "category", "price", "quantity"],
        "properties": {
          "userId": {
            "type": "string",
            "example": "641a98c12b4f1f0012345678"
          },
          "productId": {
            "type": "string",
            "example": "prod-001"
          },
          "productName": {
            "type": "string",
            "example": "Wireless Headphones"
          },
          "category": {
            "type": "string",
            "example": "electronics"
          },
          "price": {
            "type": "number",
            "format": "double",
            "example": 129.99
          },
          "quantity": {
            "type": "integer",
            "format": "int32",
            "example": 2,
            "minimum": 1
          }
        }
      },
      "CartItem": {
        "type": "object",
        "properties": {
          "productId": {
            "type": "string"
          },
          "productName": {
            "type": "string"
          },
          "category": {
            "type": "string"
          },
          "price": {
            "type": "number",
            "format": "double"
          },
          "quantity": {
            "type": "integer",
            "format": "int32"
          }
        }
      },
      "CheckoutSummary": {
        "type": "object",
        "properties": {
          "items": {
            "type": "array",
            "items": {
              "$ref": "#/components/schemas/CartItem"
            }
          },
          "subtotal": {
            "type": "number",
            "format": "double"
          },
          "uniqueCategories": {
            "type": "integer",
            "format": "int32"
          },
          "percentageDiscount": {
            "type": "number",
            "format": "double"
          },
          "diversityBonus": {
            "type": "number",
            "format": "double"
          },
          "totalDiscount": {
            "type": "number",
            "format": "double"
          },
          "finalAmount": {
            "type": "number",
            "format": "double"
          }
        }
      },
      "AuthSuccessResponse": {
        "type": "object",
        "properties": {
          "success": {
            "type": "boolean",
            "example": true
          },
          "message": {
            "type": "string",
            "example": "LoggedIn Successful."
          },
          "data": {
            "type": "string",
            "description": "JWT access token"
          }
        }
      },
      "SuccessResponse": {
        "type": "object",
        "properties": {
          "success": {
            "type": "boolean",
            "example": true
          },
          "message": {
            "type": "string",
            "example": "Success"
          },
          "data": {
            "type": "object"
          }
        }
      },
      "ErrorResponse": {
        "type": "object",
        "properties": {
          "success": {
            "type": "boolean",
            "example": false
          },
          "message": {
            "type": "string",
            "example": "Validation error"
          },
          "errors": {
            "type": "array",
            "items": {
              "type": "object",
              "properties": {
                "field": {
                  "type": "string"
                },
                "message": {
                  "type": "string"
                }
              }
            }
          }
        }
      }
    }
  },
  "paths": {
    "/users/register-user": {
      "post": {
        "tags": ["Users"],
        "summary": "Register a new user",
        "requestBody": {
          "required": true,
          "content": {
            "application/json": {
              "schema": {
                "$ref": "#/components/schemas/UserRegisterRequest"
              }
            }
          }
        },
        "responses": {
          "200": {
            "description": "User registration successful",
            "content": {
              "application/json": {
                "schema": {
                  "$ref": "#/components/schemas/AuthSuccessResponse"
                }
              }
            }
          },
          "400": {
            "description": "Validation or bad request",
            "content": {
              "application/json": {
                "schema": {
                  "$ref": "#/components/schemas/ErrorResponse"
                }
              }
            }
          },
          "500": {
            "description": "Server error",
            "content": {
              "application/json": {
                "schema": {
                  "$ref": "#/components/schemas/ErrorResponse"
                }
              }
            }
          }
        }
      }
    },
    "/users/login": {
      "post": {
        "tags": ["Users"],
        "summary": "Authenticate a user and issue a JWT",
        "requestBody": {
          "required": true,
          "content": {
            "application/json": {
              "schema": {
                "$ref": "#/components/schemas/UserLoginRequest"
              }
            }
          }
        },
        "responses": {
          "200": {
            "description": "Login successful",
            "content": {
              "application/json": {
                "schema": {
                  "$ref": "#/components/schemas/AuthSuccessResponse"
                }
              }
            }
          },
          "400": {
            "description": "Validation or authentication failed",
            "content": {
              "application/json": {
                "schema": {
                  "$ref": "#/components/schemas/ErrorResponse"
                }
              }
            }
          },
          "404": {
            "description": "User not found",
            "content": {
              "application/json": {
                "schema": {
                  "$ref": "#/components/schemas/ErrorResponse"
                }
              }
            }
          },
          "500": {
            "description": "Server error",
            "content": {
              "application/json": {
                "schema": {
                  "$ref": "#/components/schemas/ErrorResponse"
                }
              }
            }
          }
        }
      }
    },
    "/carts/items": {
      "post": {
        "tags": ["Carts"],
        "summary": "Add an item to a user's cart",
        "security": [
          {
            "BearerAuth": []
          }
        ],
        "requestBody": {
          "required": true,
          "content": {
            "application/json": {
              "schema": {
                "$ref": "#/components/schemas/AddItemRequest"
              }
            }
          }
        },
        "responses": {
          "200": {
            "description": "Item added to cart successfully",
            "content": {
              "application/json": {
                "schema": {
                  "$ref": "#/components/schemas/SuccessResponse"
                }
              }
            }
          },
          "400": {
            "description": "Validation or bad request",
            "content": {
              "application/json": {
                "schema": {
                  "$ref": "#/components/schemas/ErrorResponse"
                }
              }
            }
          },
          "401": {
            "description": "Unauthorized - missing or invalid token",
            "content": {
              "application/json": {
                "schema": {
                  "$ref": "#/components/schemas/ErrorResponse"
                }
              }
            }
          },
          "500": {
            "description": "Server error",
            "content": {
              "application/json": {
                "schema": {
                  "$ref": "#/components/schemas/ErrorResponse"
                }
              }
            }
          }
        }
      }
    },
    "/carts/items/{userId}/{productId}": {
      "delete": {
        "tags": ["Carts"],
        "summary": "Remove an item from a user's cart",
        "security": [
          {
            "BearerAuth": []
          }
        ],
        "parameters": [
          {
            "name": "userId",
            "in": "path",
            "required": true,
            "schema": {
              "type": "string"
            },
            "description": "The ID of the user whose cart item will be removed"
          },
          {
            "name": "productId",
            "in": "path",
            "required": true,
            "schema": {
              "type": "string"
            },
            "description": "The ID of the product to remove from the cart"
          }
        ],
        "responses": {
          "200": {
            "description": "Item removed from cart successfully",
            "content": {
              "application/json": {
                "schema": {
                  "$ref": "#/components/schemas/SuccessResponse"
                }
              }
            }
          },
          "400": {
            "description": "Validation or bad request",
            "content": {
              "application/json": {
                "schema": {
                  "$ref": "#/components/schemas/ErrorResponse"
                }
              }
            }
          },
          "401": {
            "description": "Unauthorized - missing or invalid token",
            "content": {
              "application/json": {
                "schema": {
                  "$ref": "#/components/schemas/ErrorResponse"
                }
              }
            }
          },
          "404": {
            "description": "Cart or item not found",
            "content": {
              "application/json": {
                "schema": {
                  "$ref": "#/components/schemas/ErrorResponse"
                }
              }
            }
          },
          "500": {
            "description": "Server error",
            "content": {
              "application/json": {
                "schema": {
                  "$ref": "#/components/schemas/ErrorResponse"
                }
              }
            }
          }
        }
      }
    },
    "/carts/checkout/{userId}": {
      "get": {
        "tags": ["Carts"],
        "summary": "Retrieve the checkout summary for a user's cart",
        "security": [
          {
            "BearerAuth": []
          }
        ],
        "parameters": [
          {
            "name": "userId",
            "in": "path",
            "required": true,
            "schema": {
              "type": "string"
            },
            "description": "The ID of the user whose cart checkout summary is requested"
          }
        ],
        "responses": {
          "200": {
            "description": "Checkout summary returned successfully",
            "content": {
              "application/json": {
                "schema": {
                  "$ref": "#/components/schemas/CheckoutSummary"
                }
              }
            }
          },
          "400": {
            "description": "Validation or bad request",
            "content": {
              "application/json": {
                "schema": {
                  "$ref": "#/components/schemas/ErrorResponse"
                }
              }
            }
          },
          "401": {
            "description": "Unauthorized - missing or invalid token",
            "content": {
              "application/json": {
                "schema": {
                  "$ref": "#/components/schemas/ErrorResponse"
                }
              }
            }
          },
          "404": {
            "description": "Cart not found",
            "content": {
              "application/json": {
                "schema": {
                  "$ref": "#/components/schemas/ErrorResponse"
                }
              }
            }
          },
          "500": {
            "description": "Server error",
            "content": {
              "application/json": {
                "schema": {
                  "$ref": "#/components/schemas/ErrorResponse"
                }
              }
            }
          }
        }
      }
    }
  }
}
